pai_sso/__init__.py
pai_sso/db.sqlite3
pai_sso/runtests.py
pai_sso/server.py
pai_sso/skeleton.py
pai_sso/app/__init__.py
pai_sso/app/settings.py
pai_sso/app/profiles/__init__.py
pai_sso/app/profiles/admin.py
pai_sso/app/profiles/apps.py
pai_sso/app/profiles/authentication.py
pai_sso/app/profiles/backends.py
pai_sso/app/profiles/context_processors.py
pai_sso/app/profiles/functions.py
pai_sso/app/profiles/middleware.py
pai_sso/app/profiles/models.py
pai_sso/app/profiles/serializers.py
pai_sso/app/profiles/urls.py
pai_sso/app/profiles/utils.py
pai_sso/app/profiles/views.py
pai_sso/app/profiles/management/__init__.py
pai_sso/app/profiles/management/commands/__init__.py
pai_sso/app/profiles/management/commands/delete_all_devices.py
pai_sso/app/profiles/management/commands/delete_user_devices.py
pai_sso/app/profiles/management/commands/reset_apigw_consumer_ids.py
pai_sso/app/profiles/migrations/0001_initial.py
pai_sso/app/profiles/migrations/0002_profile_user.py
pai_sso/app/profiles/migrations/__init__.py
pai_sso/app/profiles/tests/__init__.py
pai_sso/core/__init__.py
pai_sso/core/common.py
pai_sso/core/db.sqlite3
pai_sso/core/functions.py
pai_sso/core/models.py
pai_sso/core/permissions.py
pai_sso/core/serializers.py
pai_sso/core/settings.py
pai_sso/core/apps/__init__.py
pai_sso/core/apps/mixins.py
pai_sso/core/apps/utils.py
pai_sso/core/apps/api_gateway/__init__.py
pai_sso/core/apps/api_gateway/functions.py
pai_sso/core/apps/api_gateway/kong/__init__.py
pai_sso/core/apps/api_gateway/kong/apps.py
pai_sso/core/apps/api_gateway/kong/functions.py
pai_sso/core/apps/api_gateway/kong/tests.py
pai_sso/core/apps/devices/__init__.py
pai_sso/core/apps/devices/admin.py
pai_sso/core/apps/devices/apps.py
pai_sso/core/apps/devices/functions.py
pai_sso/core/apps/devices/models.py
pai_sso/core/apps/devices/tests.py
pai_sso/core/apps/devices/migrations/0001_initial.py
pai_sso/core/apps/devices/migrations/0002_device_user.py
pai_sso/core/apps/devices/migrations/__init__.py
pai_sso-0.0.0.dev1.dist-info/AUTHORS.rst
pai_sso-0.0.0.dev1.dist-info/LICENSE.txt
pai_sso-0.0.0.dev1.dist-info/METADATA
pai_sso-0.0.0.dev1.dist-info/WHEEL
pai_sso-0.0.0.dev1.dist-info/entry_points.txt
pai_sso-0.0.0.dev1.dist-info/top_level.txt
pai_sso-0.0.0.dev1.dist-info/RECORD
