Metadata-Version: 2.1
Name: pai-sso
Version: 0.0.0.dev1
Summary: PAI SSO
Home-page: https://bitbucket.org/pai/django-remote-templates
Author: pai
Author-email: paiuolo@gmail.com
License: mit
Project-URL: Documentation, https://pyscaffold.org/
Platform: any
Classifier: Development Status :: 4 - Beta
Classifier: Programming Language :: Python
Provides-Extra: testing
Requires-Dist: pytest ; extra == 'testing'
Requires-Dist: pytest-cov ; extra == 'testing'
